aibaba_ai_cli/__init__.py
aibaba_ai_cli/_version.py
aibaba_ai_cli/cli.py
aibaba_ai_cli/constants.py
aibaba_ai_cli/dev_scripts.py
aibaba_ai_cli/integration_template/.gitignore
aibaba_ai_cli/integration_template/LICENSE
aibaba_ai_cli/integration_template/Makefile
aibaba_ai_cli/integration_template/README.md
aibaba_ai_cli/integration_template/docs/chat.ipynb
aibaba_ai_cli/integration_template/docs/document_loaders.ipynb
aibaba_ai_cli/integration_template/docs/llms.ipynb
aibaba_ai_cli/integration_template/docs/provider.ipynb
aibaba_ai_cli/integration_template/docs/retrievers.ipynb
aibaba_ai_cli/integration_template/docs/stores.ipynb
aibaba_ai_cli/integration_template/docs/text_embedding.ipynb
aibaba_ai_cli/integration_template/docs/toolkits.ipynb
aibaba_ai_cli/integration_template/docs/tools.ipynb
aibaba_ai_cli/integration_template/docs/vectorstores.ipynb
aibaba_ai_cli/integration_template/integration_template/__init__.py
aibaba_ai_cli/integration_template/integration_template/chat_models.py
aibaba_ai_cli/integration_template/integration_template/document_loaders.py
aibaba_ai_cli/integration_template/integration_template/embeddings.py
aibaba_ai_cli/integration_template/integration_template/py.typed
aibaba_ai_cli/integration_template/integration_template/retrievers.py
aibaba_ai_cli/integration_template/integration_template/toolkits.py
aibaba_ai_cli/integration_template/integration_template/tools.py
aibaba_ai_cli/integration_template/integration_template/vectorstores.py
aibaba_ai_cli/integration_template/pyproject.toml
aibaba_ai_cli/integration_template/scripts/check_imports.py
aibaba_ai_cli/integration_template/scripts/lint_imports.sh
aibaba_ai_cli/integration_template/tests/__init__.py
aibaba_ai_cli/integration_template/tests/integration_tests/__init__.py
aibaba_ai_cli/integration_template/tests/integration_tests/test_chat_models.py
aibaba_ai_cli/integration_template/tests/integration_tests/test_compile.py
aibaba_ai_cli-0.0.40.dist-info/LICENSE
aibaba_ai_cli-0.0.40.dist-info/METADATA
aibaba_ai_cli-0.0.40.dist-info/WHEEL
aibaba_ai_cli-0.0.40.dist-info/entry_points.txt
aibaba_ai_cli-0.0.40.dist-info/RECORD
